greeummcp/__init__.py
greeummcp/cli.py
greeummcp/server.py
greeummcp/adapters/__init__.py
greeummcp/adapters/greeum_adapter.py
greeummcp/prompts/__init__.py
greeummcp/prompts/memory_prompts.py
greeummcp/resources/__init__.py
greeummcp/resources/memory_resources.py
greeummcp/tools/__init__.py
greeummcp/tools/memory_tools.py
greeummcp/tools/utility_tools.py
greeummcp-1.0.0.dist-info/licenses/LICENSE
greeummcp-1.0.0.dist-info/METADATA
greeummcp-1.0.0.dist-info/WHEEL
greeummcp-1.0.0.dist-info/entry_points.txt
greeummcp-1.0.0.dist-info/top_level.txt
greeummcp-1.0.0.dist-info/RECORD
