Metadata-Version: 2.4
Name: greeummcp
Version: 1.0.0
Summary: # GreeumMCP
Home-page: https://github.com/GreeumAI/GreeumMCP
Author: GreeumAI
Author-email: GreeumAI <contact@greeum.ai>
License: MIT
Project-URL: Homepage, https://github.com/GreeumAI/GreeumMCP
Project-URL: Documentation, https://github.com/GreeumAI/GreeumMCP/tree/main/docs
Project-URL: Repository, https://github.com/GreeumAI/GreeumMCP
Project-URL: Issues, https://github.com/GreeumAI/GreeumMCP/issues
Keywords: mcp,model-context-protocol,memory,ai,llm,greeum
Classifier: Development Status :: 5 - Production/Stable
Classifier: Intended Audience :: Developers
Classifier: License :: OSI Approved :: MIT License
Classifier: Programming Language :: Python :: 3
Classifier: Programming Language :: Python :: 3.10
Classifier: Programming Language :: Python :: 3.11
Classifier: Programming Language :: Python :: 3.12
Classifier: Topic :: Software Development :: Libraries :: Python Modules
Classifier: Topic :: Scientific/Engineering :: Artificial Intelligence
Requires-Python: >=3.10
License-File: LICENSE
Requires-Dist: greeum>=1.0.0
Requires-Dist: mcp>=1.0.0
Requires-Dist: fastapi>=0.100.0
Requires-Dist: pydantic>=2.0.0
Requires-Dist: uvicorn>=0.15.0
Requires-Dist: typer>=0.9.0
Provides-Extra: dev
Requires-Dist: pytest>=7.0.0; extra == "dev"
Requires-Dist: black>=23.0.0; extra == "dev"
Requires-Dist: mypy>=1.0.0; extra == "dev"
Dynamic: author
Dynamic: home-page
Dynamic: license-file
Dynamic: requires-python
